pyrto/__init__.py
pyrto/cli.py
pyrto/pyrto.py
pyrto-0.1.1.dist-info/METADATA
pyrto-0.1.1.dist-info/WHEEL
pyrto-0.1.1.dist-info/entry_points.txt
pyrto-0.1.1.dist-info/top_level.txt
pyrto-0.1.1.dist-info/RECORD
