Metadata-Version: 2.4
Name: pyrto
Version: 0.1.1
Summary: A package to fetch vehicle details and images based on license plate numbers
Home-page: https://github.com/shubhamshnd/pyrto
Author: Shubham Shinde
Author-email: shubhamshindesunil@gmail.com
Classifier: Programming Language :: Python :: 3
Classifier: License :: OSI Approved :: MIT License
Classifier: Operating System :: OS Independent
Requires-Python: >=3.6
Requires-Dist: requests
Requires-Dist: beautifulsoup4
Requires-Dist: Pillow
Dynamic: author
Dynamic: author-email
Dynamic: classifier
Dynamic: description
Dynamic: description-content-type
Dynamic: home-page
Dynamic: requires-dist
Dynamic: requires-python
Dynamic: summary
